.bumpversion.cfg
.gitignore
.pre-commit-config.yaml
.pylintrc
.python-version
AAA-BreakingChanges.md
CITATION.cff
HOW_TO_RELEASE.md
LICENSE.txt
README.md
pyproject.toml
release_notes.txt
uv.lock
.github/ISSUE_TEMPLATE/bug_report.md
.github/ISSUE_TEMPLATE/feature_request.md
.github/workflows/branch-docs.yml
.github/workflows/build_installer.yml
.github/workflows/config-testpypi-version.py
.github/workflows/core_tests.yml
.github/workflows/deployment.yml
.github/workflows/localize-base-urls.py
.github/workflows/rebuild-docs.yml
.github/workflows/test-deploy.yml
activitysim/__init__.py
activitysim/__main__.py
activitysim/_generated_version.py
activitysim/preconfigure.py
activitysim.egg-info/PKG-INFO
activitysim.egg-info/SOURCES.txt
activitysim.egg-info/dependency_links.txt
activitysim.egg-info/entry_points.txt
activitysim.egg-info/requires.txt
activitysim.egg-info/top_level.txt
activitysim/abm/README.md
activitysim/abm/__init__.py
activitysim/abm/misc.py
activitysim/abm/models/__init__.py
activitysim/abm/models/accessibility.py
activitysim/abm/models/atwork_subtour_destination.py
activitysim/abm/models/atwork_subtour_frequency.py
activitysim/abm/models/atwork_subtour_mode_choice.py
activitysim/abm/models/atwork_subtour_scheduling.py
activitysim/abm/models/auto_ownership.py
activitysim/abm/models/cdap.py
activitysim/abm/models/disaggregate_accessibility.py
activitysim/abm/models/free_parking.py
activitysim/abm/models/initialize.py
activitysim/abm/models/initialize_los.py
activitysim/abm/models/initialize_tours.py
activitysim/abm/models/input_checker.py
activitysim/abm/models/joint_tour_composition.py
activitysim/abm/models/joint_tour_destination.py
activitysim/abm/models/joint_tour_frequency.py
activitysim/abm/models/joint_tour_frequency_composition.py
activitysim/abm/models/joint_tour_participation.py
activitysim/abm/models/joint_tour_scheduling.py
activitysim/abm/models/location_choice.py
activitysim/abm/models/mandatory_scheduling.py
activitysim/abm/models/mandatory_tour_frequency.py
activitysim/abm/models/non_mandatory_destination.py
activitysim/abm/models/non_mandatory_scheduling.py
activitysim/abm/models/non_mandatory_tour_frequency.py
