Metadata-Version: 2.4
Name: activitysim
Version: 1.5.1
Requires-Python: >=3.10
License-File: LICENSE.txt
Requires-Dist: cytoolz>=0.8.1
Requires-Dist: multimethod<2.0
Requires-Dist: numba>=0.57
Requires-Dist: numpy<1.26,>=1.16.1
Requires-Dist: openmatrix>=0.3.4.1
Requires-Dist: pandas>=2
Requires-Dist: pandera<0.18.1,>=0.15
Requires-Dist: platformdirs
Requires-Dist: psutil>=4.1
Requires-Dist: pyarrow>=2.0
Requires-Dist: pydantic>=2.6
Requires-Dist: pypyr>=5.3
Requires-Dist: pyyaml>=5.1
Requires-Dist: requests>=2.7
Requires-Dist: scikit-learn>=1.2
Requires-Dist: setuptools>=80.9.0
Requires-Dist: sharrow>=2.15
Requires-Dist: sparse
Requires-Dist: tables>=3.9
Requires-Dist: xarray>=2024.05
Dynamic: license-file
